configparserplus/__init__.py
configparserplus/compat.py
configparserplus/main.py
configparserplus-0.0.6.dist-info/LICENSE
configparserplus-0.0.6.dist-info/METADATA
configparserplus-0.0.6.dist-info/WHEEL
configparserplus-0.0.6.dist-info/top_level.txt
configparserplus-0.0.6.dist-info/RECORD
